{
  "ChipParameters": [
    {
      "IntegrationTimeCode": 1,
      "IntegrationTime": 4.0,
      "CapacityCode": 0,
      "Capacity": 3.0,
      "CountPerMilliVoltCalibration": [
        [
        5311.17,
        5374.02,
        5264.61,
        5274.09,
        5289.37,
        5249.62,
        5275.14,
        5306.9,
        5281.71,
        5257.94,
        5264.45,
        5315.13,
        5315.77,
        5341.33,
        5348.6,
        5299.18,
        5286.36,
        5316.25,
        5292.94,
        5316.94,
        5263.64,
        5305.67,
        5319.15,
        5269.75,
        5354.0,
        5286.94,
        5247.09,
        5286.41,
        5289.44,
        5253.29,
        5272.92,
        5276.61
        ],
        [
        5312.25,
        5376.94,
        5262.74,
        5274.56,
        5284.6,
        5246.66,
        5273.95,
        5303.17,
        5278.77,
        5256.63,
        5257.41,
        5315.67,
        5313.29,
        5340.24,
        5351.13,
        5297.71,
        5284.85,
        5312.36,
        5287.37,
        5313.11,
        5259.03,
        5302.21,
        5318.82,
        5268.52,
        5348.53,
        5287.23,
        5247.82,
        5287.06,
        5288.34,
        5248.57,
        5269.42,
        5285.88
        ]
      ],
      "AmplitudeCalibration": [
        1, 1, 1, 1, 1, 1, 1, 1, 1, 1, 1, 1, 1, 1, 1, 1, 1, 1, 1, 1, 1, 1, 1, 1,
        1, 1, 1, 1, 1, 1, 1, 1
      ]
    },
    {
      "IntegrationTimeCode": 1,
      "IntegrationTime": 4.0,
      "CapacityCode": 2,
      "Capacity": 25.0,
      "CountPerMilliVoltCalibration": [
        [
        672.142,
        679.939,
        665.452,
        668.311,
        668.606,
        663.419,
        666.731,
        670.735,
        667.194,
        664.425,
        664.656,
        671.37,
        671.468,
        674.761,
        675.763,
        669.593,
        669.549,
        673.21,
        670.155,
        673.155,
        666.481,
        672.099,
        673.791,
        667.054,
        676.686,
        668.066,
        662.785,
        668.237,
        668.768,
        663.85,
        666.367,
        667.668
        ],
        [
        672.357,
        679.94,
        665.561,
        668.414,
        668.46,
        663.511,
        666.817,
        670.789,
        667.185,
        664.361,
        664.426,
        671.322,
        671.359,
        674.547,
        675.788,
        669.671,
        669.955,
        673.195,
        669.921,
        672.983,
        666.501,
        672.068,
        673.725,
        667.071,
        676.716,
        668.125,
        662.941,
        668.363,
        668.806,
        663.85,
        666.41,
        668.276
        ]
      ],
      "AmplitudeCalibration": [
        1, 1, 1, 1, 1, 1, 1, 1, 1, 1, 1, 1, 1, 1, 1, 1, 1, 1, 1, 1, 1, 1, 1, 1,
        1, 1, 1, 1, 1, 1, 1, 1
      ]
    }
  ]
}
